MANIFEST.in
README.md
setup.py
gaeio/LICENSE.txt
gaeio/README.md
gaeio/__init__.py
gaeio/cognitivegeo.png
gaeio/gaeio.png
gaeio/logo_large.png
gaeio/logo_small.png
gaeio/qrcode.pdf
gaeio/snapshot.png
gaeio.egg-info/PKG-INFO
gaeio.egg-info/SOURCES.txt
gaeio.egg-info/dependency_links.txt
gaeio.egg-info/requires.txt
gaeio.egg-info/top_level.txt
gaeio/__pycache__/__init__.cpython-36.pyc
gaeio/demo/demo.proj.npy
gaeio/demo/demo.proj.data/Horizon/hor1.hrz.npy
gaeio/demo/demo.proj.data/Horizon/hor2.hrz.npy
gaeio/demo/demo.proj.data/Horizon/hor3.hrz.npy
gaeio/demo/demo.proj.data/PointSet/hor1.pts.npy
gaeio/demo/demo.proj.data/PointSet/hor2.pts.npy
gaeio/demo/demo.proj.data/PointSet/hor3.pts.npy
gaeio/demo/demo.proj.data/PsSeismic/ps_2_shot_seis.psseis.npy
gaeio/demo/demo.proj.data/PsSeismic/ps_shot_seis.psseis.npy
gaeio/demo/demo.proj.data/Seismic/fault.seis.npy
gaeio/demo/demo.proj.data/Seismic/seis.seis.npy
gaeio/demo/demo.proj.data/Settings/settings.npy
gaeio/demo/demo.proj.data/Survey/survey.srv.npy
gaeio/src/__init__.py
gaeio/src/__pycache__/__init__.cpython-36.pyc
gaeio/src/basic/__init__.py
gaeio/src/basic/curve.py
gaeio/src/basic/data.py
gaeio/src/basic/file.py
gaeio/src/basic/image.py
gaeio/src/basic/matdict.py
gaeio/src/basic/video.py
gaeio/src/basic/__pycache__/__init__.cpython-36.pyc
gaeio/src/basic/__pycache__/__init__.cpython-37.pyc
gaeio/src/basic/__pycache__/curve.cpython-36.pyc
gaeio/src/basic/__pycache__/curve.cpython-37.pyc
gaeio/src/basic/__pycache__/data.cpython-36.pyc
gaeio/src/basic/__pycache__/data.cpython-37.pyc
gaeio/src/basic/__pycache__/file.cpython-36.pyc
gaeio/src/basic/__pycache__/image.cpython-36.pyc
gaeio/src/basic/__pycache__/image.cpython-37.pyc
gaeio/src/basic/__pycache__/matdict.cpython-36.pyc
gaeio/src/basic/__pycache__/matdict.cpython-37.pyc
gaeio/src/basic/__pycache__/video.cpython-36.pyc
gaeio/src/basic/__pycache__/video.cpython-37.pyc
gaeio/src/core/__init__.py
gaeio/src/core/keyboard.py
gaeio/src/core/settings.py
gaeio/src/core/__pycache__/__init__.cpython-36.pyc
gaeio/src/core/__pycache__/__init__.cpython-37.pyc
gaeio/src/core/__pycache__/keyboard.cpython-36.pyc
